entra_expiry_checker/__init__.py
entra_expiry_checker/config.py
entra_expiry_checker/main.py
entra_expiry_checker/models.py
entra_expiry_checker/orchestrator.py
entra_expiry_checker/clients/__init__.py
entra_expiry_checker/clients/graph_client.py
entra_expiry_checker/clients/table_client.py
entra_expiry_checker/services/__init__.py
entra_expiry_checker/services/app_discovery.py
entra_expiry_checker/services/email_service.py
entra_expiry_checker/services/secret_checker.py
entra_expiry_checker-1.1.0.dist-info/licenses/LICENSE
entra_expiry_checker-1.1.0.dist-info/METADATA
entra_expiry_checker-1.1.0.dist-info/WHEEL
entra_expiry_checker-1.1.0.dist-info/entry_points.txt
entra_expiry_checker-1.1.0.dist-info/top_level.txt
entra_expiry_checker-1.1.0.dist-info/RECORD
