Metadata-Version: 2.4
Name: entra-expiry-checker
Version: 1.1.0
Summary: Microsoft Entra App Registration Credential Expiry Checker
Author-email: Tom Burgess <tom@tburgess.co.uk>
Maintainer-email: Tom Burgess <tom@tburgess.co.uk>
License: MIT
Project-URL: Homepage, https://github.com/brgsstm/entra-expiry-checker
Project-URL: Documentation, https://github.com/brgsstm/entra-expiry-checker#readme
Project-URL: Repository, https://github.com/brgsstm/entra-expiry-checker
Project-URL: Bug Tracker, https://github.com/brgsstm/entra-expiry-checker/issues
Keywords: azure,microsoft-graph,entra-id,app-registration,credential-expiry,monitoring
Classifier: Development Status :: 5 - Production/Stable
Classifier: Intended Audience :: Developers
Classifier: Intended Audience :: System Administrators
Classifier: License :: OSI Approved :: MIT License
Classifier: Operating System :: OS Independent
Classifier: Programming Language :: Python :: 3
Classifier: Programming Language :: Python :: 3.11
Classifier: Programming Language :: Python :: 3.12
Classifier: Programming Language :: Python :: 3.13
Classifier: Topic :: System :: Monitoring
Classifier: Topic :: System :: Systems Administration
Classifier: Topic :: Utilities
Requires-Python: >=3.11
License-File: LICENSE
Requires-Dist: python-decouple
Requires-Dist: requests
Requires-Dist: azure-identity
Requires-Dist: azure-data-tables
Requires-Dist: sendgrid
Provides-Extra: dev
Requires-Dist: pytest; extra == "dev"
Requires-Dist: pytest-cov; extra == "dev"
Requires-Dist: black; extra == "dev"
Requires-Dist: flake8; extra == "dev"
Requires-Dist: mypy; extra == "dev"
Requires-Dist: pre-commit; extra == "dev"
Requires-Dist: build; extra == "dev"
Requires-Dist: twine; extra == "dev"
Requires-Dist: wheel; extra == "dev"
Dynamic: license-file
